{
  "project": {
    "name": "Attentix AI",
    "tagline": "Enterprise AI Infrastructure for Data-Driven Decision Making",
    "domain": "www.attentixai.com",
    "description": "A web-native pitch deck for venture capitalists and enterprise customers"
  },
  "designSystem": {
    "name": "Precision Noir",
    "philosophy": "Merging Umbrel's atmospheric premium feel with Linear's systematic engineering precision",
    "colorPalette": {
      "primary": {
        "dark": "#0F0F0F",
        "darker": "#050505",
        "surface": "#1A1A1A"
      },
      "accent": {
        "electric": "#00D9FF",
        "cyan": "#00B4D8",
        "teal": "#0099B6"
      },
      "semantic": {
        "success": "#10B981",
        "warning": "#F59E0B",
        "error": "#EF4444",
        "info": "#3B82F6"
      },
      "neutral": {
        "50": "#F9FAFB",
        "100": "#F3F4F6",
        "200": "#E5E7EB",
        "300": "#D1D5DB",
        "400": "#9CA3AF",
        "500": "#6B7280",
        "600": "#4B5563",
        "700": "#2D3748",
        "800": "#1F2937",
        "900": "#111827"
      }
    },
    "typography": {
      "fontFamily": {
        "sans": "\"Inter\", -apple-system, BlinkMacSystemFont, \"Segoe UI\", Roboto, sans-serif",
        "mono": "\"JetBrains Mono\", \"Courier New\", monospace"
      },
      "scale": {
        "h1": { "size": "3.5rem", "weight": 700, "lineHeight": 1.1 },
        "h2": { "size": "2.5rem", "weight": 700, "lineHeight": 1.2 },
        "h3": { "size": "1.875rem", "weight": 600, "lineHeight": 1.3 },
        "body": { "size": "1rem", "weight": 400, "lineHeight": 1.6 },
        "bodySmall": { "size": "0.875rem", "weight": 400, "lineHeight": 1.5 },
        "label": { "size": "0.75rem", "weight": 600, "lineHeight": 1.4, "letterSpacing": "0.5px" }
      }
    },
    "spacing": {
      "xs": "0.25rem",
      "sm": "0.5rem",
      "md": "1rem",
      "lg": "1.5rem",
      "xl": "2rem",
      "2xl": "3rem",
      "3xl": "4rem",
      "4xl": "6rem"
    },
    "components": {
      "button": {
        "primary": {
          "bg": "#00D9FF",
          "text": "#0F0F0F",
          "hover": "#00B4D8"
        },
        "secondary": {
          "bg": "transparent",
          "text": "#00D9FF",
          "border": "#00D9FF",
          "hover": "#00B4D8"
        }
      },
      "card": {
        "bg": "#1A1A1A",
        "border": "#2D3748",
        "borderRadius": "0.5rem"
      }
    }
  },
  "pages": {
    "1_homepage": {
      "title": "Attentix AI — Enterprise Intelligence Infrastructure",
      "slug": "/",
      "purpose": "Main landing page introducing the product and value proposition",
      "sections": [
        "hero",
        "value_props",
        "how_it_works_flow",
        "capabilities",
        "use_cases_preview",
        "cta_investors_and_customers",
        "footer"
      ],
      "contentFile": "pages/1_homepage.md",
      "targetAudience": ["All visitors", "Investors", "Enterprise customers"]
    },
    "2_technology": {
      "title": "Technology Deep-Dive — The Moat",
      "slug": "/technology",
      "purpose": "Technical VC page - explains the competitive advantage and technical architecture",
      "sections": [
        "hero_moat",
        "core_architecture",
        "data_processing_pipeline",
        "ai_models_framework",
        "security_compliance",
        "performance_metrics",
        "patent_status",
        "cta_tech_discussion",
        "footer"
      ],
      "contentFile": "pages/2_technology.md",
      "targetAudience": ["Technical VCs", "Enterprise CTOs", "Technical architects"]
    },
    "3_for_investors": {
      "title": "For Investors",
      "slug": "/investors",
      "purpose": "Investor-focused page with market opportunity, business model, and traction",
      "sections": [
        "hero_investor",
        "market_opportunity",
        "business_model",
        "traction_milestones",
        "use_of_proceeds",
        "the_ask",
        "pitch_deck_download_gated",
        "schedule_meeting",
        "footer"
      ],
      "contentFile": "pages/3_for_investors.md",
      "targetAudience": ["VCs", "Angel investors", "Strategic partners"],
      "access": "public",
      "gatedContent": ["pitch_deck_download"]
    },
    "4_use_cases": {
      "title": "Use Cases",
      "slug": "/use-cases",
      "purpose": "Detailed use cases by industry and company size",
      "sections": [
        "hero_use_cases",
        "enterprise_ai_ops",
        "finance_risk_prediction",
        "healthcare_diagnostics",
        "supply_chain_optimization",
        "customer_success_stories_preview",
        "cta_book_demo",
        "footer"
      ],
      "contentFile": "pages/4_use_cases.md",
      "targetAudience": ["Enterprise customers", "Industry-specific decision makers"]
    },
    "5_about": {
      "title": "About Attentix AI",
      "slug": "/about",
      "purpose": "Company mission, vision, and founding story",
      "sections": [
        "hero_mission",
        "founding_story",
        "vision_2030",
        "values_culture",
        "company_timeline",
        "industry_recognition",
        "careers_link",
        "footer"
      ],
      "contentFile": "pages/5_about.md",
      "targetAudience": ["All visitors", "Prospective employees"],
      "includeTeam": false,
      "note": "Team section skipped for now — will add later"
    },
    "6_get_started": {
      "title": "Get Started",
      "slug": "/get-started",
      "purpose": "Documentation and quick-start guide for evaluating the product",
      "sections": [
        "hero_developer",
        "features_overview",
        "integration_options",
        "pricing_tiers_preview",
        "quickstart_deployment",
        "documentation_cta",
        "demo_video",
        "footer"
      ],
      "contentFile": "pages/6_get_started.md",
      "targetAudience": ["Technical teams", "Enterprise evaluators"]
    },
    "7_contact": {
      "title": "Contact & Support",
      "slug": "/contact",
      "purpose": "Contact form, support channels, and general inquiries",
      "sections": [
        "hero_contact",
        "contact_form",
        "contact_methods",
        "support_resources",
        "status_page_link",
        "footer"
      ],
      "contentFile": "pages/7_contact.md",
      "targetAudience": ["All visitors"]
    }
  },
  "flowArchitecture": {
    "description": "VC Funnel Architecture - Each page maps to specific investor questions",
    "funnelMap": {
      "awareness": ["1_homepage"],
      "interest": ["2_technology", "4_use_cases"],
      "evaluation": ["3_for_investors", "6_get_started"],
      "decision": ["7_contact"]
    },
    "numberedFlow": {
      "section": "How It Works",
      "steps": [
        { "number": "1.0", "label": "Ingest", "description": "Auto-connect to your data sources and extract patterns" },
        { "number": "2.0", "label": "Focus", "description": "Identify signal in noise with our proprietary AI framework" },
        { "number": "3.0", "label": "Predict", "description": "Generate actionable forecasts and recommendations" },
        { "number": "4.0", "label": "Act", "description": "Execute decisions with built-in workflow automation" }
      ]
    }
  },
  "trustSignals": {
    "approach": "industry-focused and factual capability statements",
    "signals": [
      {
        "type": "capability",
        "text": "Built for Fortune 500 data environments"
      },
      {
        "type": "compliance",
        "text": "Enterprise-grade security: SOC2 compliant architecture"
      },
      {
        "type": "scale",
        "text": "Processing 10B+ data points in testing"
      },
      {
        "type": "reliability",
        "text": "99.99% uptime SLA"
      }
    ],
    "technologyPartners": [
      "Google Cloud Platform",
      "AWS",
      "Supabase",
      "PostgreSQL"
    ]
  },
  "buildConfig": {
    "framework": "Stitch",
    "contentApproach": "Markdown-first - each page has a .md content brief before generation",
    "buildLoop": "stitch-loop + design-md with baton files for systematic page-by-page generation",
    "outputFormat": "Static HTML/CSS with component reusability",
    "deploymentTarget": "Vercel / Netlify",
    "seo": {
      "lang": "en",
      "charset": "utf-8",
      "ogImage": "/og-default.png",
      "appleTouchIcon": "/apple-touch-icon.png"
    },
    "analytics": {
      "gtag": "G-XXXXXXXXXX",
      "hotjar": "3700000"
    }
  },
  "buildSequence": [
    {
      "phase": 1,
      "page": "1_homepage",
      "status": "pending",
      "priority": "critical"
    },
    {
      "phase": 2,
      "page": "2_technology",
      "status": "pending",
      "priority": "high"
    },
    {
      "phase": 3,
      "page": "3_for_investors",
      "status": "pending",
      "priority": "high"
    },
    {
      "phase": 4,
      "page": "4_use_cases",
      "status": "pending",
      "priority": "medium"
    },
    {
      "phase": 5,
      "page": "5_about",
      "status": "pending",
      "priority": "medium"
    },
    {
      "phase": 6,
      "page": "6_get_started",
      "status": "pending",
      "priority": "medium"
    },
    {
      "phase": 7,
      "page": "7_contact",
      "status": "pending",
      "priority": "medium"
    }
  ]
}
